README.md
setup.py
asgard_api_plugin_metrics_fluentd.egg-info/PKG-INFO
asgard_api_plugin_metrics_fluentd.egg-info/SOURCES.txt
asgard_api_plugin_metrics_fluentd.egg-info/dependency_links.txt
asgard_api_plugin_metrics_fluentd.egg-info/entry_points.txt
asgard_api_plugin_metrics_fluentd.egg-info/top_level.txt
fluentdmetrics/__init__.py
fluentdmetrics/blueprint.py
fluentdmetrics/fluentd.py
fluentdmetrics/plugin.py
fluentdmetrics/api/__init__.py
fluentdmetrics/api/routes.py