Metadata-Version: 1.1
Name: asgard-api-plugin-metrics-fluentd
Version: 0.2.0
Summary: Asgard API endpoints to get Fluentd metrics
Home-page: https://github.com/B2W-BIT/asgard-api-plugin-metrics-fluentd
Author: Dalton Barreto
Author-email: daltonmatos@gmail.com
License: MIT
Platform: UNKNOWN
Classifier: Programming Language :: Python :: 3.6
